{
  "version": "7",
  "dialect": "postgresql",
  "entries": [
    {
      "idx": 0,
      "version": "7",
      "when": 1773576469507,
      "tag": "0000_overconfident_mindworm",
      "breakpoints": true
    },
    {
      "idx": 1,
      "version": "7",
      "when": 1773783150066,
      "tag": "0001_thankful_professor_monster",
      "breakpoints": true
    },
    {
      "idx": 2,
      "version": "7",
      "when": 1773920873664,
      "tag": "0002_nostalgic_nick_fury",
      "breakpoints": true
    },
    {
      "idx": 3,
      "version": "7",
      "when": 1773946010000,
      "tag": "0003_breezy_zarek",
      "breakpoints": true
    },
    {
      "idx": 4,
      "version": "7",
      "when": 1773946010199,
      "tag": "0004_mixed_speedball",
      "breakpoints": true
    },
    {
      "idx": 5,
      "version": "7",
      "when": 1774010566284,
      "tag": "0005_pretty_magneto",
      "breakpoints": true
    },
    {
      "idx": 6,
      "version": "7",
      "when": 1774025193608,
      "tag": "0006_ancient_triton",
      "breakpoints": true
    },
    {
      "idx": 7,
      "version": "7",
      "when": 1774125631874,
      "tag": "0007_right_norman_osborn",
      "breakpoints": true
    },
    {
      "idx": 8,
      "version": "7",
      "when": 1775390152261,
      "tag": "0008_chunky_pandemic",
      "breakpoints": true
    }
  ]
}